LICENSE.txt
README.md
setup.cfg
setup.py
diabric/__init__.py
diabric/config.py
diabric/ec2.py
diabric/files.py
diabric/venv.py
diabric.egg-info/PKG-INFO
diabric.egg-info/SOURCES.txt
diabric.egg-info/dependency_links.txt
diabric.egg-info/requires.txt
diabric.egg-info/top_level.txt