Metadata-Version: 1.1
Name: diabric
Version: 0.1.6
Summary: Diabolically atomic Python Fabric fabfile tasks and utilities.
Home-page: https://github.com/todddeluca/diabric
Author: Todd Francis DeLuca
Author-email: todddeluca@yahoo.com
License: MIT
Keywords: fabric fabfile boto ec2 virtualenv python wsgi webapp deployment
Platform: UNKNOWN
Classifier: License :: OSI Approved :: MIT License
Classifier: Development Status :: 2 - Pre-Alpha
Classifier: Programming Language :: Python :: 2
Classifier: Programming Language :: Python :: 2.7
